README.rst
setup.py
hecho/__init__.py
hecho/daemon.py
hecho/hecho.py
hecho.egg-info/PKG-INFO
hecho.egg-info/SOURCES.txt
hecho.egg-info/dependency_links.txt
hecho.egg-info/entry_points.txt
hecho.egg-info/requires.txt
hecho.egg-info/top_level.txt