Metadata-Version: 1.0
Name: hecho
Version: 0.1.4
Summary: Simple fast HTTP echo server
Home-page: https://github.com/pdrb/hecho
Author: Pedro Buteri Gonring
Author-email: pedro@bigode.net
License: MIT
Keywords: fast http echo server
Platform: UNKNOWN
